bayesbuilding/__init__.py
bayesbuilding/model_selection.py
bayesbuilding/models.py
bayesbuilding/plotting.py
bayesbuilding/wrapper.py
bayesbuilding-0.1.0.dist-info/LICENCE.md
bayesbuilding-0.1.0.dist-info/METADATA
bayesbuilding-0.1.0.dist-info/WHEEL
bayesbuilding-0.1.0.dist-info/top_level.txt
bayesbuilding-0.1.0.dist-info/RECORD
