Metadata-Version: 2.1
Name: bayesbuilding
Version: 0.1.0
Summary: Bayesian approach for building energy modeling
Home-page: https://github.com/BuildingEnergySimulationTools/bayesbuilding
Author: Nobatek/INEF4
Author-email: bdurandestebe@nobatek.inef4.com
License: License :: OSI Approved :: BSD License
Classifier: Development Status :: 4 - Beta
Classifier: Intended Audience :: Developers
Classifier: Topic :: Scientific/Engineering
Classifier: Programming Language :: Python :: 3.10
Classifier: Programming Language :: Python :: 3.11
Requires-Python: >=3.10
License-File: LICENCE.md
Requires-Dist: pymc >=5.10.3
Requires-Dist: pandas >=1.3.4
Requires-Dist: numpy >=1.26.3
Requires-Dist: arviz >=0.18.0
Requires-Dist: matplotlib >=3.7.5
Requires-Dist: plotly >=5.13.1
